tsugite/__init__.py
tsugite/cli.py
tsugite/loader.py
tsugite/utils.py
tsugite/backend/__init__.py
tsugite/backend/backend.py
tsugite/backend/cyphal_backend.py
tsugite/backend/dronecan_backend.py
tsugite/backend/dummy_backend.py
tsugite/backend/registry.py
tsugite/configs/examples/example.yaml
tsugite/configs/panels/gps.yaml
tsugite/configs/panels/node_monitor.yaml
tsugite/configs/panels/pwm.yaml
tsugite/configs/panels/vibrations_node_63.yaml
tsugite/ui/__init__.py
tsugite/ui/desktop/__init__.py
tsugite/ui/desktop/pyside_window.py
tsugite/ui/desktop/welcome_panel.py
tsugite/ui/desktop/widgets.py
tsugite-0.6.1.dist-info/METADATA
tsugite-0.6.1.dist-info/WHEEL
tsugite-0.6.1.dist-info/entry_points.txt
tsugite-0.6.1.dist-info/top_level.txt
tsugite-0.6.1.dist-info/RECORD
