Metadata-Version: 2.4
Name: tsugite
Version: 0.6.1
Summary: System-oriented dashboards for DroneCAN & Cyphal (YAML-powered)
Author-email: Dmitry Ponomarev <ponomarevda96@gmail.com>
License-Expression: MIT
Project-URL: Homepage, https://github.com/PonomarevDA/tsugite
Project-URL: Issues, https://github.com/PonomarevDA/tsugite/issues
Keywords: uav,drone,dronecan,cyphal,dashboard,telemetry,yaml
Classifier: Programming Language :: Python :: 3
Classifier: Programming Language :: Python :: 3 :: Only
Classifier: Operating System :: OS Independent
Classifier: Typing :: Typed
Requires-Python: >=3.9
Requires-Dist: pyyaml>=6.0.3
Provides-Extra: dronecan
Requires-Dist: PySide6>=6.10.0; extra == "dronecan"
Requires-Dist: folium>=0.20.0; extra == "dronecan"
Requires-Dist: pyqtgraph>=0.13.7; extra == "dronecan"
Requires-Dist: python-can==4.3; extra == "dronecan"
Requires-Dist: pyserial>=3.5.0; extra == "dronecan"
Requires-Dist: dronecan>=1.0.27; extra == "dronecan"
Requires-Dist: setuptools==80.9.0; extra == "dronecan"
Provides-Extra: cyphal
Requires-Dist: PySide6>=6.10.0; extra == "cyphal"
Requires-Dist: folium>=0.20.0; extra == "cyphal"
Requires-Dist: pyqtgraph>=0.13.7; extra == "cyphal"
Requires-Dist: yakut>=0.14.1; extra == "cyphal"
Provides-Extra: all
Requires-Dist: PySide6>=6.10.0; extra == "all"
Requires-Dist: folium>=0.20.0; extra == "all"
Requires-Dist: pyqtgraph>=0.13.7; extra == "all"
Requires-Dist: python-can==4.3; extra == "all"
Requires-Dist: pyserial>=3.5.0; extra == "all"
Requires-Dist: dronecan>=1.0.27; extra == "all"
Requires-Dist: setuptools==80.9.0; extra == "all"
Requires-Dist: build; extra == "all"
Requires-Dist: twine; extra == "all"
Requires-Dist: pylint>=4.0.2; extra == "all"
Provides-Extra: desktop-dronecan
Requires-Dist: PySide6>=6.10.0; extra == "desktop-dronecan"
Requires-Dist: folium>=0.20.0; extra == "desktop-dronecan"
Requires-Dist: pyqtgraph>=0.13.7; extra == "desktop-dronecan"
Requires-Dist: python-can==4.3; extra == "desktop-dronecan"
Requires-Dist: pyserial>=3.5.0; extra == "desktop-dronecan"
Requires-Dist: dronecan>=1.0.27; extra == "desktop-dronecan"
Requires-Dist: setuptools==80.9.0; extra == "desktop-dronecan"
